pycleaner/__init__.py
pycleaner/cli.py
pycleaner/core.py
pycleaner/data.py
pycleaner/utils.py
pycleaner_cli-0.1.2.dist-info/METADATA
pycleaner_cli-0.1.2.dist-info/WHEEL
pycleaner_cli-0.1.2.dist-info/entry_points.txt
pycleaner_cli-0.1.2.dist-info/top_level.txt
pycleaner_cli-0.1.2.dist-info/RECORD
